Workbook

Sheet Resumo
A1: Virgin Details, Lda — Orçamento Odoo
A2: Parâmetro Global · Consultoria Informática · 25/05/2026
A4: 1. IMPLEMENTAÇÃO — Custo Único (Fase 1 — Faturação)
A5: Rúbrica | B5: Valor (€) | C5: Notas
A6: Serviços — Fase 1 (Faturação) | B6: 5400 | C6: Detalhe em sheet Serviços — 80h / 10 dias / ~6 semanas
A7: Software Odoo Enterprise — 1.º Ano | B7: =Software!G6 | C7: ⚠ Placeholder — confirmar c/ Stefano Biglieri (Odoo Enterprise 5 users, Odoo SH)
A8: Plugin Certificação AT — 1.º Ano | B8: =Software!G12 | C8: ⚠ Placeholder — confirmar c/ Stefano Biglieri (plugin AT certificação faturas)
A9: TOTAL 1.º ANO (sem IVA) | B9: 7752
A10: IVA (23%) | B10: 1782.96
A11: TOTAL 1.º ANO (com IVA) | B11: 9534.96 | C11: Valor final faturável
A13: 2. EXPLORAÇÃO — Valores Anuais (a partir do 2.º Ano)
A14: Rúbrica | B14: Valor (€) | C14: Notas
A15: Software Odoo Enterprise (anos seguintes) | B15: =Software!H6 | C15: ⚠ Placeholder — confirmar c/ Stefano
A16: Plugin Certificação AT (anos seguintes) | B16: =Software!H12 | C16: ⚠ Placeholder — confirmar c/ Stefano
A17: Apoio Após Venda — Parâmetro Global | B17: =Config!$B$12 | C17: Contrato anual suporte e manutenção
A18: TOTAL ANUAL (sem IVA) | B18: =SUM(B15:B17)
A20: 3. FASES SEGUINTES (Indicativo — a confirmar após go-live Fase 1)
A21: Rúbrica | B21: Valor (€) | C21: Notas
A22: Serviços — Fase 2: Operação Comercial (indicativo) | B22: 4360 | C22: CRM, Pipedrive [POR VALIDAR], Compras, Inventário — ver sheet Serviços
A23: SUBTOTAL FASE 2 (sem IVA) | B23: 4360
A24: Serviços — Fase 3: Expansão (indicativo) [POR VALIDAR] | B24: 4680 | C24: BoM, Multiempresa (Starplast SRLE), Analítica, Módulos — ver sheet Serviços
A25: SUBTOTAL FASE 3 (sem IVA) | B25: 4680
A26: TOTAL FASES SEGUINTES (Fase 2 + Fase 3, indicativo) | B26: 9040
A27: Nota: Licenciamento Odoo e plugin AT — valores placeholder, confirmar c/ Stefano Biglieri. Fase 2 e Fase 3 sujeitas a levantamento de requisitos adicional. Cada fase tem orçamento e proposta própria após go-live da anterior. Proposta válida até 20/06/2026.

Sheet Software
A1: Licenciamento Odoo — Proposta de Software
A2: ⚠ Valores a confirmar por Stefano Biglieri — preencher células amarelas C5, C10, C11
A3: Descrição | B3: Utilizadores | C3: Valor/Mês/User (€) | D3: Desconto 1.º Ano | E3: Valor c/ Desc. Mensal | F3: Total Mensal (€) | G3: Total 1.º Ano (€) | H3: Total Anos Seg. (€)
A4: Licenciamento Odoo Enterprise (Odoo SH)
A5: Odoo Enterprise + Odoo SH | B5: =Config!$B$7 | C5: 38 | D5: =Config!$B$8 | E5: =C5*(1-D5) | F5: =E5*B5 | G5: =F5*12 | H5: =C5*B5*12
A6: TOTAL Odoo Enterprise | G6: =G5 | H6: =H5
A8: Plugin de Certificação de Faturas (AT)
A10: Subscrição base plugin AT (anual) | B10: 1 | C10: 420 | D10: =Config!$B$8 | E10: =C10*(1-D10)/12 | F10: =E10 | G10: =C10*(1-D10) | H10: =C10
A11: Taxa por utilizador — plugin AT (anual) | B11: =Config!$B$7 | C11: 48 | D11: =Config!$B$8 | E11: =C11*(1-D11)/12 | F11: =E11*B11 | G11: =C11*(1-D11)*B11 | H11: =C11*B11
A12: TOTAL Plugin AT | G12: =G10+G11 | H12: =H10+H11
A15: TOTAL SOFTWARE | G15: =G6+G12 | H15: =H6+H12

Sheet Serviços
A1: Detalhe de Serviços — Implementação Odoo
A2: FASE 1 — Faturação (Virgin Details, Lda)
A3: Fase | B3: Descrição | C3: Horas | D3: Dias | E3: Valor (€)
A4: 01.Gestão de Projeto | B4: Kick-off, acompanhamento quinzenal, reporting, encerramento de fase | C4: 8 | D4: 1 | E4: 720
A5: 02.Kick-off + Configuração | B5: Setup empresa, 5 utilizadores, grupos de acesso, e-mail e templates | C5: 12 | D5: 1.5 | E5: 780
A6: 03.Contactos e Produtos | B6: Clientes, fornecedores, produtos e serviços; importação de PHC GO e Excel | C6: 8 | D6: 1 | E6: 520
A7: 04.Vendas e Faturação | B7: Orçamentos, encomendas, faturas, notas de crédito, faturação certificada AT | C7: 16 | D7: 2 | E7: 1040
A8: 05.Financeiro l10n_pt | B8: Plano contas PT, IVA, SAF-T, plugin AT, condições pagamento, banca | C8: 16 | D8: 2 | E8: 1040
A9: 06.Migração PHC GO | B9: Importação produtos, clientes/fornecedores, saldos em aberto de PHC GO | C9: 16 | D9: 2 | E9: 1040
A10: 07.Testes + Formação + Arranque | B10: Testes faturação end-to-end, formação 5 utilizadores, suporte go-live | C10: 4 | D10: 0.5 | E10: 260
A16: SUBTOTAL FASE 1 | C16: 80 | D16: 10 | E16: 5400
A18: FASE 2 — Operação Comercial (Indicativo — após go-live Fase 1)
A19: Fase | B19: Descrição | C19: Horas | D19: Dias | E19: Valor (€)
A20: 08.CRM | B20: Pipeline, fases, probabilidades, templates e-mail, atividades, dashboards | C20: 8 | D20: 1 | E20: 520
A21: 09.Migração Pipedrive | B21: Exportação, mapeamento e importação CRM Pipedrive → Odoo [POR VALIDAR] | C21: 16 | D21: 2 | E21: 1040
A22: 10.Compras | B22: Fornecedores europeus, preços custo, lead times, regras MTO | C22: 8 | D22: 1 | E22: 520
A23: 11.Inventário e Logística | B23: Armazém Maia, rotas MTO, receção Itália, dropshipping Espanha | C23: 16 | D23: 2 | E23: 1040
A24: 12.Testes + Formação F2 | B24: Testes end-to-end Fase 2, formação, suporte go-live | C24: 8 | D24: 1 | E24: 520
A25: 13.Gestão de Projeto F2 | B25: Acompanhamento Fase 2 (taxa GP) | C25: 8 | D25: 1 | E25: 720
A26: SUBTOTAL FASE 2 (base, indicativo) | C26: 64 | D26: 8 | E26: 4360
A28: FASE 3 — Expansão (Indicativo [POR VALIDAR] — após go-live Fase 2)
A29: Fase | B29: Descrição | C29: Horas | D29: Dias | E29: Valor (€)
A30: 14.Manufatura (BoM) | B30: Listas de Materiais, Ordens de Fabrico, controlo componentes | C30: 16 | D30: 2 | E30: 1040
A31: 15.Multiempresa — Starplast SRLE | B31: Configuração 2.ª empresa, utilizadores partilhados, intercompany | C31: 24 | D31: 3 | E31: 1560
A32: 16.Contabilidade Analítica | B32: Analítica por projeto / marca (4 marcas) / cliente | C32: 16 | D32: 2 | E32: 1040
A33: 17.Módulos Adicionais | B33: Sign, Barcode, Documents, Helpdesk — prioridade a definir [POR VALIDAR] | C33: 16 | D33: 2 | E33: 1040
A34: SUBTOTAL FASE 3 (base, indicativo) | C34: 72 | D34: 9 | E34: 4680
A36: TOTAL GERAL SERVIÇOS | C36: 216 | D36: 27 | E36: 14440

Sheet Cronograma
A1: Cronograma Indicativo — Implementação Odoo
A2: Fase | B2: Descrição | C2: Dias | D2: Sem. Início | E2: Sem. Fim | F2: Observações
A3: 01.Gestão de Projeto | B3: Kick-off e acompanhamento | C3: 1 | D3: 1 | E3: 6 | F3: Transversal à Fase 1
A4: 02.Kick-off + Configuração | B4: Setup empresa e utilizadores | C4: 1.5 | D4: 1 | E4: 1
A5: 03.Contactos e Produtos | B5: Contactos, produtos, importação | C5: 1 | D5: 2 | E5: 2
A6: 04.Vendas e Faturação | B6: Orçamentos, faturas, AT | C6: 2 | D6: 2 | E6: 3
A7: 05.Financeiro l10n_pt | B7: Plano contas, SAF-T, banca | C7: 2 | D7: 3 | E7: 4
A8: 06.Migração PHC GO | B8: Produtos, clientes, saldos | C8: 2 | D8: 4 | E8: 5 | F8: Cliente fornece dados em Excel limpo
A9: 07.Testes + Formação + Arranque | B9: Testes, formação, go-live | C9: 0.5 | D9: 5 | E9: 6
A15: FASE 1 TOTAL | C15: 10
A17: FASE 2 — Operação Comercial (Indicativo — após go-live Fase 1)
A18: 08.CRM | B18: Pipeline e dashboards | C18: 1 | D18: 1 | E18: 1
A19: 09.Migração Pipedrive | B19: Histórico CRM Pipedrive → Odoo | C19: 2 | D19: 1 | E19: 2 | F19: [POR VALIDAR]
A20: 10.Compras | B20: Compras e fornecedores | C20: 1 | D20: 2 | E20: 2
A21: 11.Inventário e Logística | B21: Armazém e rotas | C21: 2 | D21: 3 | E21: 4
A22: 12.Testes + Formação F2 | B22: Testes e go-live Fase 2 | C22: 1 | D22: 4 | E22: 5
A23: 13.Gestão Projeto F2 | B23: Acompanhamento Fase 2 | C23: 1 | D23: 1 | E23: 5 | F23: Transversal
A24: FASE 2 TOTAL (indicativo) | C24: 8
A26: FASE 3 — Expansão (Indicativo [POR VALIDAR] — após go-live Fase 2)
A27: 14.Manufatura (BoM) | B27: Listas materiais e fabrico | C27: 2 | D27: 1 | E27: 2 | F27: [POR VALIDAR]
A28: 15.Multiempresa — Starplast SRLE | B28: 2.ª empresa, intercompany | C28: 3 | D28: 2 | E28: 4 | F28: [POR VALIDAR]
A29: 16.Contabilidade Analítica | B29: Analítica por projeto/marca | C29: 2 | D29: 4 | E29: 5
A30: 17.Módulos Adicionais | B30: Sign, Barcode, Helpdesk — a def. | C30: 2 | D30: 5 | E30: 6 | F30: [POR VALIDAR] — a definir
A31: FASE 3 TOTAL (indicativo) | C31: 9

Sheet Config
A1: CONFIGURAÇÃO — Parâmetros Editáveis
A3: Parâmetro | B3: Valor | C3: Descrição
A4: Taxa Consultor (€/h) | B4: 65 | C4: CS_Consultor — taxa horária base
A5: Taxa Gestor de Projeto (€/h) | B5: 90 | C5: CS_Gestor — taxa horária base
A6: Horas por Dia | B6: 8 | C6: Horas úteis por dia de trabalho
A7: N.º Utilizadores Odoo | B7: 5 | C7: Utilizadores ativos na licença
A8: Desconto 1.º Ano Odoo (%) | B8: 25/05/2026 | C8: Desconto aplicado no 1.º ano de licença
A9: Data da Proposta | B9: 20/05/2026 | C9: Data de emissão do orçamento
A10: Válido até | B10: 20/06/2026 | C10: Prazo de validade da proposta
A11: IVA (%) | B11: 0.23 | C11: Taxa de IVA aplicável
A12: Apoio Após Venda (€/ano) | B12: 2400 | C12: Valor anual do contrato de suporte

Sheet DB
A1: Empresa | B1: Fase | C1: Descrição | D1: Tipo | E1: Perfil | F1: Taxa (€/h) | G1: Horas | H1: Dias | I1: Valor (€) | J1: Por Validar | K1: Notas
A2: Virgin Details, Lda | B2: 01.Gestão de Projeto | C2: Kick-off interno e cliente; reuniões quinzenais; reporting; encerramento de fase | D2: Gestão de Projeto | E2: CS_Gestor | F2: 90 | G2: 8 | H2: 1 | I2: 720
A3: Virgin Details, Lda | B3: 02.Kick-off + Configuração | C3: Setup empresa; 5 utilizadores; grupos de acesso; e-mail; templates | D3: Parametrização | E3: CS_Consultor | F3: 65 | G3: 12 | H3: 1.5 | I3: 780
A4: Virgin Details, Lda | B4: 03.Contactos e Produtos | C4: Clientes, fornecedores; produtos e serviços; importação de PHC GO e Excel | D4: Parametrização | E4: CS_Consultor | F4: 65 | G4: 8 | H4: 1 | I4: 520 | K4: Importação a partir de PHC GO
A5: Virgin Details, Lda | B5: 04.Vendas e Faturação | C5: Templates orçamento; encomendas de venda; faturas; notas de crédito; faturação certificada AT | D5: Parametrização | E5: CS_Consultor | F5: 65 | G5: 16 | H5: 2 | I5: 1040
A6: Virgin Details, Lda | B6: 05.Financeiro l10n_pt | C6: Plano de contas PT; grupos IVA; SAF-T; plugin certificação AT; condições pagamento; adiantamentos; banca | D6: Parametrização | E6: CS_Consultor | F6: 65 | G6: 16 | H6: 2 | I6: 1040 | K6: Plugin AT licenciado separadamente — confirmar antes do kick-off
A7: Virgin Details, Lda | B7: 06.Migração PHC GO | C7: Importação catálogo produtos; clientes e fornecedores; saldos em aberto de PHC GO | D7: Migração | E7: CS_Consultor | F7: 65 | G7: 16 | H7: 2 | I7: 1040 | K7: Cliente fornece dados em Excel limpo
A8: Virgin Details, Lda | B8: 07.Testes + Formação + Arranque | C8: Testes faturação end-to-end; formação 5 utilizadores; suporte go-live; documentação | D8: Formação | E8: CS_Consultor | F8: 65 | G8: 4 | H8: 0.5 | I8: 260
A9: Virgin Details, Lda | B9: SUBTOTAL — Fase 1 (Faturação) | G9: 80 | H9: 10 | I9: 5400
A10: Virgin Details, Lda | B10: 08.CRM | C10: Pipeline; fases e probabilidades; templates e-mail por fase; atividades; dashboards | D10: Parametrização | E10: CS_Consultor | F10: 65 | G10: 8 | H10: 1 | I10: 520
A11: Virgin Details, Lda | B11: 09.Migração Pipedrive | C11: Exportação, mapeamento e importação de contactos e histórico CRM do Pipedrive para Odoo | D11: Migração | E11: CS_Consultor | F11: 65 | G11: 16 | H11: 2 | I11: 1040 | J11: SIM | K11: Esforço depende do volume e qualidade dos dados Pipedrive
A12: Virgin Details, Lda | B12: 10.Compras | C12: Fornecedores europeus (4 marcas); preços custo; lead times; regras MTO; encomenda automática | D12: Parametrização | E12: CS_Consultor | F12: 65 | G12: 8 | H12: 1 | I12: 520
A13: Virgin Details, Lda | B13: 11.Inventário e Logística | C13: Armazém Maia PT; rotas MTO+Comprar; receção Itália (Starplast/Sunerg); dropshipping Espanha | D13: Parametrização | E13: CS_Consultor | F13: 65 | G13: 16 | H13: 2 | I13: 1040
A14: Virgin Details, Lda | B14: 12.Testes + Formação Fase 2 | C14: Testes end-to-end Fase 2; formação por perfil; suporte go-live | D14: Formação | E14: CS_Consultor | F14: 65 | G14: 8 | H14: 1 | I14: 520
A15: Virgin Details, Lda | B15: 13.Gestão de Projeto Fase 2 | C15: Acompanhamento Fase 2 (taxa GP) | D15: Gestão de Projeto | E15: CS_Gestor | F15: 90 | G15: 8 | H15: 1 | I15: 720
A16: Virgin Details, Lda | B16: SUBTOTAL — Fase 2 (Operação Comercial) | G16: 64 | H16: 8 | I16: 4360
A17: Expansão (Fase 3) | B17: 14.Manufatura (BoM) | C17: Listas de Materiais; Ordens de Fabrico; controlo componentes; custo produto final | D17: Parametrização | E17: CS_Consultor | F17: 65 | G17: 16 | H17: 2 | I17: 1040 | J17: SIM | K17: Âmbito depende de levantamento dos kits mais frequentes
A18: Expansão (Fase 3) | B18: 15.Multiempresa — Starplast SRLE | C18: Configuração 2.ª empresa do grupo; utilizadores partilhados; transações intercompany | D18: Parametrização | E18: CS_Consultor | F18: 65 | G18: 24 | H18: 3 | I18: 1560 | J18: SIM | K18: Depende de confirmação estrutura legal Starplast SRLE
A19: Expansão (Fase 3) | B19: 16.Contabilidade Analítica | C19: Analítica por projeto / marca (4 marcas) / cliente | D19: Parametrização | E19: CS_Consultor | F19: 65 | G19: 16 | H19: 2 | I19: 1040 | J19: SIM
A20: Expansão (Fase 3) | B20: 17.Módulos Adicionais | C20: Sign (aprovação eletrónica), Barcode (armazém), Documents, Helpdesk — a definir | D20: Parametrização | E20: CS_Consultor | F20: 65 | G20: 16 | H20: 2 | I20: 1040 | J20: SIM | K20: A orçamentar após levantamento de prioridades
A21: Expansão (Fase 3) | B21: SUBTOTAL — Fase 3 (Expansão) | G21: 72 | H21: 9 | I21: 4680
B22: TOTAL GERAL | G22: 216 | H22: 27 | I22: 14440

Sheet tarefas
A1: Tipo | B1: Fator
A2: Consultadoria | B2: 1
A3: Desenvolvimento | B3: 1
A4: Formação | B4: 1
A5: Gestão de Projeto | B5: 1
A6: Migração | B6: 1
A7: Orçamentação | B7: 1
A8: Parametrização | B8: 1
A9: Testes | B9: 1

Sheet artigos
A1: Código | B1: Taxa (€/h)
A2: CS_Consultor | B2: =Config!$B$4
A3: CS_Gestor | B3: =Config!$B$5

Sheet Empresa
A1: Resumo por Empresa / Fase
A2: Empresa / Fase | B2: Horas | C2: Valor (€)
A3: Virgin Details, Lda — Fase 1 (Faturação) | B3: 80 | C3: 5400
A4: Virgin Details, Lda — Fase 2 (Operação Comercial, indicativo) | B4: 64 | C4: 4360
A5: Expansão — Fase 3 (indicativo [POR VALIDAR]) | B5: 72 | C5: 4680
A6: Total Geral | B6: 216 | C6: 14440
