Workbook

Sheet Resumo
A1: Rúbrica | B1: Valor
A2: Serviços | B2: =+GETPIVOTDATA(" Valor",Empresa!$A$3) -> 2080
A4: Software Odoo | B4: =+Software!G5 -> 215.28
A6: Certificação PT | B6: =+Software!G13 -> 374.4
A8: Total | B8: =B2+B4+B6 -> 2669.68
A11: Exploração ( Valores Anuais ) | B11: Valor
A13: Software Odoo | B13: =+Software!H5 -> 268.8
A15: Certificação PT | B15: =+Software!H13 -> 468
A17: Apoio Após Venda | B17: 0
A19: Total | B19: =SUM(B13:B17) -> 736.8

Sheet Software
B2: Licenciamento Odoo Enterprise
B4: Utilizadores | C4: Valor / Ano | D4: Desconto 1º Ano | E4: Valor Mensal | F4: Total Mensal | G4: Total 1º Ano | H4: Total Anos Seguintes
B5: 1 | C5: 22.4 | D5: 0.2 | E5: 17.94 | F5: =+E5*B5 -> 17.94 | G5: =+F5*12 -> 215.28 | H5: =+C5*B5*12 -> 268.8
B8: Plugin Faturação
B10: Utilizadores | C10: Valor / Ano | D10: Desconto 1º Ano | E10: Valor Mensal | F10: Total Mensal | G10: Total 1º Ano | H10: Total Anos Seguintes
B11: Subscrição | C11: 420 | D11: 0.2 | E11: =+(C11*0.8)/12 -> 28 | F11: =+E11 -> 28 | G11: =+C11-(+C11*D11) -> 336 | H11: =+C11 -> 420
B12: =B5 -> 1 | C12: 48 | D12: 0.2 | E12: =+(C12*0.8)/12 -> 3.2 | F12: =+E12*B12*12 -> 38.4 | G12: =+E12*B12*12 -> 38.4 | H12: =+C12*B12 -> 48
F13: Total | G13: =SUM(G11:G12) -> 374.4 | H13: =+H11+H12 -> 468
B16: Plugin Faturação + Contabilidade + Salários
B18: Utilizadores | C18: Valor / Ano | D18: Desconto 1º Ano | E18: Valor Mensal | F18: Total Mensal | G18: Total 1º Ano | H18: Total Anos Seguintes
B19: Subscrição | C19: 840 | D19: 0.2 | E19: =+(C19*0.8)/12 -> 56 | F19: =+E19 -> 56 | G19: =+C19-(+C19*D19) -> 672 | H19: =+C19 -> 840
B20: =+B12 -> 1 | C20: 108 | D20: 0.2 | E20: =+(C20*0.8)/12 -> 7.2 | F20: =+E20*B20*12 -> 86.4 | G20: =+E20*B20*12 -> 86.4 | H20: =+C20*B20 -> 108
F21: Total | G21: =+G20+G20 -> 172.8 | H21: =+H19+H20 -> 948

Sheet Serviços
A1: 4 | B1: (Tudo)
A4: Empresa | B4: Fase | C4: Rúbrica | D4: H | E4: Valor
A5: [Nome da Empresa] | B5: 01.Set-up | C5: [Descrição da Rúbrica Exemplo 1] | D5: 8 | E5: 1040
B6: 01.Set-up Total | D6: 8 | E6: 1040
B7: 02.Levantamento de requisitos | C7: [Descrição da Rúbrica Exemplo 2] | D7: 8 | E7: 1040
B8: 02.Levantamento de requisitos Total | D8: 8 | E8: 1040
A9: [Nome da Empresa] Total | D9: 16 | E9: 2080
A10: (em branco) | B10: (em branco) | C10: (em branco)
B11: (em branco) Total
A12: (em branco) Total
A13: Total Geral | D13: 16 | E13: 2080

Sheet Cronograma
A1: 4 | B1: (Tudo)
A3: Soma de D
A4: Empresa | B4: Fase | C4: Rúbrica | D4: Total | F4: Semana 1 | G4: Semana 2 | H4: Semana 3 | I4: Semana 4 | J4: Semana 5 | K4: Semana 6 | L4: Semana 7 | M4: Semana 8 | N4: Semana 9 | O4: Semana 10 | P4: Semana 11 | Q4: Semana 12 | R4: Semana 13 | S4: Semana 14
A5: [Nome da Empresa] | B5: 01.Set-up | D5: 1
B6: 02.Levantamento de requisitos | D6: 1
A7: [Nome da Empresa] Total | D7: 2
A8: (em branco) | B8: (em branco) | C8: (em branco)
B9: (em branco) Total
A10: (em branco) Total
A11: Total Geral | D11: 2

Sheet Empresa
A1: 4 | B1: (Tudo)
A4: Empresa | B4: H | C4: Valor
A5: [Nome da Empresa] | B5: 16 | C5: 2080
A6: (em branco)
A7: Total Geral | B7: 16 | C7: 2080

Sheet DB
A1: Empresa | B1: Fase | C1: Rúbrica | D1: 2 | E1: 3 | F1: 4 | G1: DE | H1: CR | I1: TR | J1: FR | K1: Valor | L1: H | M1: D | N1: DEF | O1: =SUM(K2:K3) -> 2080 | P1: =SUM(L2:L3) -> 16 | Q1: =O1/P1 -> 130
A2: [Nome da Empresa] | B2: 01.Set-up | C2: [Descrição da Rúbrica Exemplo 1] | D2: Paremeterização | E2: Consultor | F2: CS_Consultor | G2: 0 | H2: =(VLOOKUP(F2,artigos!A:B,2)*L2) -> 520 | I2: 8 | J2: 0 | K2: =((H2*VLOOKUP(D2,tarefas!A:B,2))+IF(AND((VLOOKUP(F2,artigos!A:F,6))=1,I2>0),(VLOOKUP(F2,artigos!A:E,5)),0))*((1 - (VLOOKUP(D2,tarefas!A:C,3)/2)) +((VLOOKUP(D2,tarefas!A:C,3)/20) * G2 )) -> 1040 | L2: =I2* (1 +((VLOOKUP(D2,tarefas!A:D,4)/20) * J2)) -> 8 | M2: =+L2/8 -> 1 | N2: 0
A3: [Nome da Empresa] | B3: 02.Levantamento de requisitos | C3: [Descrição da Rúbrica Exemplo 2] | D3: Consultadoria | E3: Consultor | F3: CS_Consultor | G3: 0 | H3: =(VLOOKUP(F3,artigos!A:B,2)*L3) -> 520 | I3: 8 | J3: 0 | K3: =((H3*VLOOKUP(D3,tarefas!A:B,2))+IF(AND((VLOOKUP(F3,artigos!A:F,6))=1,I3>0),(VLOOKUP(F3,artigos!A:E,5)),0))*((1 - (VLOOKUP(D3,tarefas!A:C,3)/2)) +((VLOOKUP(D3,tarefas!A:C,3)/20) * G3 )) -> 1040 | L3: =I3* (1 +((VLOOKUP(D3,tarefas!A:D,4)/20) * J3)) -> 8 | M3: =+L3/8 -> 1 | N3: 0

Sheet tarefas
A1: Consultadoria | B1: 2 | C1: 0 | D1: 0
A2: Desenvolvimento | B2: 2 | C2: 0 | D2: 0
A3: Formação | B3: 2 | C3: 0 | D3: 0
A4: Investigação | B4: 2 | C4: 0 | D4: 0 | H4: dificuldade | I4: factor de risco
A5: Orçamentação | B5: 2 | C5: 0 | D5: 0
A6: Paremeterização | B6: 2 | C6: 0 | D6: 0
A7: Suporte | B7: 2 | C7: 0 | D7: 0
A8: Validacao | B8: 2 | C8: 0 | D8: 0

Sheet artigos
A1: CS_Consultor | B1: 65 | C1: 0 | D1: 0 | E1: 0 | F1: 0
A2: CS_Formador | B2: 65 | C2: 0 | D2: 0 | E2: 0 | F2: 0
A3: Gestor projecto | B3: 90 | C3: 0 | D3: 0 | E3: 0 | F3: 0
